b_logger/__init__.py
b_logger/blog.py
b_logger/config.py
b_logger/integrations.py
b_logger/plugin.py
b_logger/runtime.py
b_logger/entities/__init__.py
b_logger/entities/attachments.py
b_logger/entities/exceptions.py
b_logger/entities/modules.py
b_logger/entities/prints.py
b_logger/entities/reports.py
b_logger/entities/statuses.py
b_logger/entities/steps.py
b_logger/entities/tests.py
b_logger/generators/__init__.py
b_logger/generators/html_gen.py
b_logger/generators/report_gen.py
b_logger/templates/__init__.py
b_logger/templates/base_macros.html
b_logger/templates/base_template.html
b_logger/templates/icon.svg
b_logger/templates/scripts.js
b_logger/templates/styles.css
b_logger/templates/summary_macros.html
b_logger/templates/summary_template.html
b_logger/utils/__init__.py
b_logger/utils/basedatamodel.py
b_logger/utils/browser_adapters.py
b_logger/utils/contextdecorator.py
b_logger/utils/dotdict.py
b_logger/utils/formatters.py
b_logger/utils/json_handler.py
b_logger/utils/paths.py
b_logger/utils/py_addons.py
pytest_b_logger-1.2.3.dist-info/licenses/LICENSE
pytest_b_logger-1.2.3.dist-info/METADATA
pytest_b_logger-1.2.3.dist-info/WHEEL
pytest_b_logger-1.2.3.dist-info/entry_points.txt
pytest_b_logger-1.2.3.dist-info/top_level.txt
pytest_b_logger-1.2.3.dist-info/RECORD
