Metadata-Version: 2.4
Name: pytest-b-logger
Version: 1.2.3
Summary: BLogger is a Pytest plugin for enhanced test logging and generating convenient and lightweight reports.
Author-email: "Serg Pudikov (serpuhovvv)" <pudikovserg@gmail.com>
Maintainer-email: "Serg Pudikov (serpuhovvv)" <pudikovserg@gmail.com>
License-Expression: Apache-2.0
Project-URL: Repository, https://github.com/serpuhovvv/b_logger
Classifier: Framework :: Pytest
Classifier: Programming Language :: Python :: 3.12
Requires-Python: >=3.9
License-File: LICENSE
Requires-Dist: pytest
Requires-Dist: pyyaml
Requires-Dist: filelock
Requires-Dist: Jinja2
Requires-Dist: python-dateutil
Requires-Dist: tzdata
Provides-Extra: extra
Requires-Dist: pytest-xdist; extra == "extra"
Requires-Dist: selenium; extra == "extra"
Requires-Dist: playwright; extra == "extra"
Requires-Dist: pytest-playwright; extra == "extra"
Requires-Dist: allure-pytest; extra == "extra"
Requires-Dist: qase-pytest; extra == "extra"
Dynamic: license-file
